README.txt
setup.py
xmlutils/__init__.py
xmlutils/console.py
xmlutils/xml2csv.py
xmlutils/xml2json.py
xmlutils/xml2sql.py
xmlutils.egg-info/PKG-INFO
xmlutils.egg-info/SOURCES.txt
xmlutils.egg-info/dependency_links.txt
xmlutils.egg-info/entry_points.txt
xmlutils.egg-info/top_level.txt